stateman/__init__.py
stateman/__main__.py
stateman-1.3.1.dist-info/METADATA
stateman-1.3.1.dist-info/WHEEL
stateman-1.3.1.dist-info/entry_points.txt
stateman-1.3.1.dist-info/RECORD
