Metadata-Version: 2.3
Name: stateman
Version: 1.3.1
Summary: This module provides tools to track changes in the content of a directory and create compact binary patches that can be used to synchronize another copy of that directory.
License: MIT
Author: vpuhoff
Author-email: vpuhoff@live.ru
Classifier: Programming Language :: Python :: 3
Classifier: License :: OSI Approved :: MIT License
Classifier: Operating System :: OS Independent
Classifier: Development Status :: 4 - Beta
Classifier: Intended Audience :: Developers
Classifier: Topic :: Software Development :: Libraries :: Python Modules
Classifier: Topic :: Utilities
